DESC.rst
MANIFEST.in
README.md
setup.py
cext/_cext.pyx
cext/_mih.pyx
cext/cext.c
cext/cext.h
cext/common.h
cext/hamdist.h
cext/mih.cpp
cext/mih.h
hdidx/__init__.py
hdidx/distance.py
hdidx/util.py
hdidx.egg-info/PKG-INFO
hdidx.egg-info/SOURCES.txt
hdidx.egg-info/dependency_links.txt
hdidx.egg-info/requires.txt
hdidx.egg-info/top_level.txt
hdidx/encoder/__init__.py
hdidx/encoder/pq.py
hdidx/encoder/sh.py
hdidx/indexer/__init__.py
hdidx/indexer/hamming.py
hdidx/indexer/vq.py
hdidx/storage/__init__.py
hdidx/storage/lmdb_storage.py
hdidx/storage/mem_storage.py
tests/test_cext.py
tests/test_indexer.py
tools/hdidx_build
tools/hdidx_index