Metadata-Version: 1.0
Name: hdidx
Version: 0.2.8.1
Summary: ANN Search in High-Dimensional Spaces
Home-page: http://wanji.me/hdidx
Author: WAN Ji
Author-email: wanji@live.com
License: LICENSE.md
Platform: UNKNOWN
